thonny_friendly-0.0.7.data/data/requirements.txt
thonnycontrib/thonny_friendly/FakeAssistant.py
thonnycontrib/thonny_friendly/GenericErrorHelper.py
thonnycontrib/thonny_friendly/__init__.py
thonnycontrib/thonny_friendly/parser.py
thonny_friendly-0.0.7.dist-info/METADATA
thonny_friendly-0.0.7.dist-info/WHEEL
thonny_friendly-0.0.7.dist-info/top_level.txt
thonny_friendly-0.0.7.dist-info/RECORD
